{
  "cui": "C0086692",
  "cui_name": "Benign Neoplasm",
  "incidence_per_100k": null,
  "prevalence_per_100k": null,
  "metric_type": null,
  "total_cases_per_year": null,
  "confidence": 0.0,
  "is_subtype": false,
  "parent_disease": null,
  "reasoning": "Umbrella term covering highly heterogeneous benign tumors (lipomas, fibromas, hemangiomas, skin tumors, colonic polyps, etc.) with vastly different incidence rates, clinical significance, surveillance practices, and diagnostic criteria. Too broad to estimate meaningfully without specification of tumor type or anatomical location.",
  "data_quality": "none",
  "geographic_variation": "high",
  "year_specific": false,
  "data_year": null,
  "source": null,
  "source_url": null,
  "source_type": null
}
