[
  {
    "cui": "C3495488",
    "cui_name": "Axenfeld-Rieger syndrome",
    "incidence_per_100k": 0.5,
    "prevalence_per_100k": null,
    "metric_type": "incidence",
    "total_cases_per_year": 40000,
    "confidence": 0.6,
    "is_subtype": false,
    "parent_disease": "Anterior Segment Dysgenesis Syndromes",
    "reasoning": "Rare genetic syndrome with anterior segment eye abnormalities. Estimated ~1 per 200,000 births (0.5 per 100k population), based on clinical case frequency and genetic epidemiology. No large population-based registry available.",
    "data_quality": "moderate",
    "geographic_variation": "low",
    "year_specific": false,
    "data_year": null,
    "source": null,
    "source_url": null,
    "source_type": null
  }
]
