{
  "cui": "C0004943",
  "cui_name": "Behcet Syndrome",
  "incidence_per_100k": 0.64,
  "prevalence_per_100k": null,
  "metric_type": "incidence",
  "total_cases_per_year": 51200,
  "confidence": 0.62,
  "is_subtype": false,
  "parent_disease": null,
  "reasoning": "Reporting incidence. Global average ~0.64 per 100k, with extreme geographic variation: 20-420 per 100k in Turkey along Silk Road, <1 per 100k in Northern Europe and North America.",
  "data_quality": "moderate",
  "geographic_variation": "high",
  "year_specific": false,
  "data_year": null,
  "source": "Yazici H et al. (2010). Behcet syndrome: a contemporary view. Nat Rev Rheumatol. 6:261-269",
  "source_url": "https://pubmed.ncbi.nlm.nih.gov/20308005/",
  "source_type": "literature"
}
