{
  "cui": "C0005695",
  "cui_name": "Bladder Neoplasm",
  "incidence_per_100k": 9.2,
  "prevalence_per_100k": null,
  "metric_type": "incidence",
  "total_cases_per_year": 736000,
  "confidence": 0.78,
  "is_subtype": false,
  "parent_disease": null,
  "reasoning": "Broader term encompassing all bladder tumors (benign and malignant). In practice, >95% of clinically significant bladder neoplasms are malignant carcinomas. Incidence ~9.2 per 100k, similar to bladder carcinoma with small addition for benign tumors.",
  "data_quality": "strong",
  "geographic_variation": "moderate",
  "year_specific": true,
  "data_year": 2005,
  "source": "GLOBOCAN 2005 (IARC) for malignant tumors",
  "source_url": "https://gco.iarc.fr/",
  "source_type": "registry"
}
