{
  "cui": "C1868683",
  "cui_name": "B-Cell Malignancy, Low-Grade",
  "incidence_per_100k": 10.0,
  "total_cases_per_year": 800000,
  "confidence": 0.65,
  "is_subtype": true,
  "parent_disease": "B-cell Malignancy",
  "reasoning": "Low-grade B-cell lymphomas including follicular lymphoma, small lymphocytic lymphoma/CLL, and marginal zone subtypes with combined estimated incidence ~10 per 100k from cancer registries.",
  "data_quality": "moderate",
  "geographic_variation": "moderate",
  "year_specific": false,
  "data_year": null
}